pyrfid_dlr/__init__.py
pyrfid_dlr/pyrfid.py
pyrfid_dlr-1.3.dist-info/COPYING
pyrfid_dlr-1.3.dist-info/LICENSE
pyrfid_dlr-1.3.dist-info/METADATA
pyrfid_dlr-1.3.dist-info/WHEEL
pyrfid_dlr-1.3.dist-info/top_level.txt
pyrfid_dlr-1.3.dist-info/RECORD
